svml/__init__.py
svml/client.py
svml/setup.py
svml/schemas/__init__.py
svml/schemas/analyze.py
svml/schemas/auth.py
svml/schemas/common.py
svml/schemas/compare.py
svml/schemas/correct.py
svml/schemas/custom_prompts.py
svml/schemas/generate.py
svml/schemas/refine.py
svml/schemas/validate.py
svml-1.0.3.dist-info/licenses/LICENSE.txt
svml-1.0.3.dist-info/METADATA
svml-1.0.3.dist-info/WHEEL
svml-1.0.3.dist-info/top_level.txt
svml-1.0.3.dist-info/RECORD
