Metadata-Version: 2.4
Name: svml
Version: 1.0.3
Summary: Python SDK for the SVML.dev API, enabling generation, validation, correction, and analysis of Semantic Vector Markup Language documents.
Author-email: Jasdeep Jaitla <jasdeep@svml.dev>
Project-URL: Homepage, https://svml.dev
Project-URL: Repository, https://github.com/svml-dev/svml-python
Classifier: Programming Language :: Python :: 3
Classifier: License :: OSI Approved :: MIT License
Classifier: Operating System :: OS Independent
Classifier: Development Status :: 4 - Beta
Classifier: Intended Audience :: Developers
Classifier: Topic :: Software Development :: Libraries :: Python Modules
Classifier: Topic :: Text Processing :: Markup
Requires-Python: >=3.7
License-File: LICENSE.txt
Requires-Dist: requests
Requires-Dist: pydantic
Dynamic: license-file
